foliant/preprocessors/plantuml.py
foliantcontrib.plantuml-1.0.10.dist-info/LICENSE
foliantcontrib.plantuml-1.0.10.dist-info/METADATA
foliantcontrib.plantuml-1.0.10.dist-info/WHEEL
foliantcontrib.plantuml-1.0.10.dist-info/top_level.txt
foliantcontrib.plantuml-1.0.10.dist-info/RECORD
