Metadata-Version: 2.1
Name: foliantcontrib.plantuml
Version: 1.0.10
Summary: PlantUML diagrams preprocessor for Foliant.
Home-page: https://github.com/foliant-docs/foliantcontrib.plantuml
Author: Artemy Lomov
Author-email: artemy@lomov.ru
License: MIT
Platform: any
Classifier: Development Status :: 5 - Production/Stable
Classifier: Environment :: Console
Classifier: Intended Audience :: Developers
Classifier: License :: OSI Approved :: MIT License
Classifier: Operating System :: OS Independent
Classifier: Programming Language :: Python
Classifier: Topic :: Documentation
Classifier: Topic :: Utilities
Requires-Dist: foliant (>=1.0.8)
Requires-Dist: foliantcontrib.utils (>=1.0.2)
